LICENSE-MIT
MANIFEST.in
README.md
setup.py
cms_bootstrap3/__init__.py
cms_bootstrap3/models.py
cms_bootstrap3/templates/bootstrap/components/paginator.html
cms_bootstrap3/templates/bootstrap/includes/breadcrumb-row.html
cms_bootstrap3/templates/bootstrap/includes/language-chooser.html
cms_bootstrap3/templates/bootstrap/includes/nav-navbar.html
cms_bootstrap3/templates/bootstrap/includes/nav-secondary.html
cms_bootstrap3/templates/bootstrap/includes/ng-nav-navbar.html
cms_bootstrap3/templates/bootstrap/menu/breadcrumb.html
cms_bootstrap3/templates/bootstrap/menu/navbar.html
cms_bootstrap3/templates/bootstrap/menu/ng-navbar.html
cms_bootstrap3/templatetags/__init__.py
cms_bootstrap3/templatetags/bootstrap_tags.py
djangocms_bootstrap3.egg-info/PKG-INFO
djangocms_bootstrap3.egg-info/SOURCES.txt
djangocms_bootstrap3.egg-info/dependency_links.txt
djangocms_bootstrap3.egg-info/not-zip-safe
djangocms_bootstrap3.egg-info/requires.txt
djangocms_bootstrap3.egg-info/top_level.txt