Metadata-Version: 2.1
Name: djangocms-bootstrap3
Version: 0.4
Summary: Templates and templatetags to be used with django-CMS and Bootstrap3.
Home-page: https://github.com/jrief/djangocms-bootstrap3
Author: Jacob Rief
Author-email: jacob.rief@gmail.com
License: LICENSE-MIT
Platform: OS Independent
Classifier: Development Status :: 4 - Beta
Classifier: Environment :: Web Environment
Classifier: Framework :: Django
Classifier: Intended Audience :: Developers
Classifier: License :: OSI Approved :: MIT License
Classifier: Operating System :: OS Independent
Classifier: Programming Language :: Python
Classifier: Topic :: Internet :: WWW/HTTP :: Dynamic Content
Classifier: Programming Language :: Python :: 2.7
Classifier: Programming Language :: Python :: 3.4
Classifier: Programming Language :: Python :: 3.5
Classifier: Programming Language :: Python :: 3.6
